[
  {
    "created_at": "2011-11-08T10:28:36Z",
    "id": 1,
    "name": "#db533d",
    "updated_at": "2011-11-08T10:28:36Z",
    "value": "#db533d"
  },
  {
    "created_at": "2011-11-08T10:28:36Z",
    "id": 2,
    "name": "#86475e",
    "updated_at": "2011-11-08T10:28:36Z",
    "value": "#86475e"
  },
  {
    "created_at": "2011-11-08T10:28:36Z",
    "id": 3,
    "name": "#afa9ad",
    "updated_at": "2011-11-08T10:28:36Z",
    "value": "#afa9ad"
  },
  {
    "created_at": "2011-11-08T10:28:36Z",
    "id": 4,
    "name": "#e9c54b",
    "updated_at": "2011-11-08T10:28:36Z",
    "value": "#e9c54b"
  },
  {
    "created_at": "2011-11-08T10:28:36Z",
    "id": 5,
    "name": "#64a353",
    "updated_at": "2011-11-08T10:28:36Z",
    "value": "#64a353"
  },
  {
    "created_at": "2011-11-08T10:28:36Z",
    "id": 6,
    "name": "#c36d3b",
    "updated_at": "2011-11-08T10:28:36Z",
    "value": "#c36d3b"
  },
  {
    "created_at": "2011-11-08T10:28:36Z",
    "id": 7,
    "name": "#ee8587",
    "updated_at": "2011-11-08T10:28:36Z",
    "value": "#ee8587"
  },
  {
    "created_at": "2011-11-08T10:28:36Z",
    "id": 8,
    "name": "#357391",
    "updated_at": "2011-11-08T10:28:36Z",
    "value": "#357391"
  },
  {
    "created_at": "2011-11-08T10:28:36Z",
    "id": 9,
    "name": "#67c095",
    "updated_at": "2011-11-08T10:28:36Z",
    "value": "#67c095"
  },
  {
    "created_at": "2011-11-08T10:28:36Z",
    "id": 10,
    "name": "#4eaea8",
    "updated_at": "2011-11-08T10:28:36Z",
    "value": "#4eaea8"
  },
  {
    "created_at": "2011-11-08T10:28:36Z",
    "id": 11,
    "name": "#f15a5b",
    "updated_at": "2011-11-08T10:28:36Z",
    "value": "#f15a5b"
  },
  {
    "created_at": "2011-11-08T10:28:36Z",
    "id": 12,
    "name": "#44adc6",
    "updated_at": "2011-11-08T10:28:36Z",
    "value": "#44adc6"
  },
  {
    "created_at": "2011-11-08T10:28:36Z",
    "id": 13,
    "name": "#9a7fba",
    "updated_at": "2011-11-08T10:28:36Z",
    "value": "#9a7fba"
  },
  {
    "created_at": "2011-11-08T10:28:36Z",
    "id": 14,
    "name": "#e7de21",
    "updated_at": "2011-11-08T10:28:36Z",
    "value": "#e7de21"
  },
  {
    "created_at": "2011-11-08T10:28:36Z",
    "id": 15,
    "name": "#c1a574",
    "updated_at": "2011-11-08T10:28:36Z",
    "value": "#c1a574"
  },
  {
    "created_at": "2011-11-08T10:28:36Z",
    "id": 16,
    "name": "#d4d1c2",
    "updated_at": "2011-11-08T10:28:36Z",
    "value": "#d4d1c2"
  },
  {
    "created_at": "2011-11-08T10:28:36Z",
    "id": 17,
    "name": "#2f723e",
    "updated_at": "2011-11-08T10:28:36Z",
    "value": "#2f723e"
  },
  {
    "created_at": "2011-11-08T10:28:36Z",
    "id": 18,
    "name": "#a0a96a",
    "updated_at": "2011-11-08T10:28:36Z",
    "value": "#a0a96a"
  },
  {
    "created_at": "2011-11-08T10:28:36Z",
    "id": 19,
    "name": "#f68b1f",
    "updated_at": "2011-11-08T10:28:36Z",
    "value": "#f68b1f"
  },
  {
    "created_at": "2011-11-08T10:28:37Z",
    "id": 20,
    "name": "#a5932b",
    "updated_at": "2011-11-08T10:28:37Z",
    "value": "#a5932b"
  },
  {
    "created_at": "2011-11-08T10:28:37Z",
    "id": 21,
    "name": "#c14f52",
    "updated_at": "2011-11-08T10:28:37Z",
    "value": "#c14f52"
  },
  {
    "created_at": "2011-11-08T10:28:37Z",
    "id": 22,
    "name": "#738f57",
    "updated_at": "2011-11-08T10:28:37Z",
    "value": "#738f57"
  },
  {
    "created_at": "2011-11-08T10:28:37Z",
    "id": 23,
    "name": "#e18256",
    "updated_at": "2011-11-08T10:28:37Z",
    "value": "#e18256"
  },
  {
    "created_at": "2011-11-08T10:28:37Z",
    "id": 24,
    "name": "#dbb727",
    "updated_at": "2011-11-08T10:28:37Z",
    "value": "#dbb727"
  },
  {
    "created_at": "2011-11-08T10:28:37Z",
    "id": 25,
    "name": "#008eb0",
    "updated_at": "2011-11-08T10:28:37Z",
    "value": "#008eb0"
  },
  {
    "created_at": "2011-11-08T10:28:37Z",
    "id": 26,
    "name": "#967448",
    "updated_at": "2011-11-08T10:28:37Z",
    "value": "#967448"
  },
  {
    "created_at": "2011-11-08T10:28:37Z",
    "id": 27,
    "name": "#c2c76c",
    "updated_at": "2011-11-08T10:28:37Z",
    "value": "#c2c76c"
  }
]
